sourcelocation/__init__.py
sourcelocation/diff.py
sourcelocation/fileline.py
sourcelocation/location.py
sourcelocation/py.typed
sourcelocation/utils.py
sourcelocation-1.1.7.dist-info/LICENSE
sourcelocation-1.1.7.dist-info/METADATA
sourcelocation-1.1.7.dist-info/WHEEL
sourcelocation-1.1.7.dist-info/RECORD
